phonexia_audio_manipulation_detection_client.py
phonexia_audio_manipulation_detection_client-2.0.2.dist-info/METADATA
phonexia_audio_manipulation_detection_client-2.0.2.dist-info/WHEEL
phonexia_audio_manipulation_detection_client-2.0.2.dist-info/entry_points.txt
phonexia_audio_manipulation_detection_client-2.0.2.dist-info/top_level.txt
phonexia_audio_manipulation_detection_client-2.0.2.dist-info/RECORD
