Metadata-Version: 2.4
Name: phonexia-audio-manipulation-detection-client
Version: 2.0.2
Summary: Audio Manipulation Detection Client
Author-email: Phonexia <info@phonexia.com>
Keywords: grpc,stt,speech-to-text,text,antispoofing,audio-manipulation
Requires-Python: >=3.9
Requires-Dist: more-itertools>=10.6.0
Requires-Dist: phonexia-grpc>=2.27.1
Requires-Dist: soundfile>=0.12.1
Requires-Dist: numpy>=1.24.3
Requires-Dist: typer>=0.12.3
